stparser/__init__.py
stparser/stparser.py
stparser-0.2.0.dist-info/WHEEL
stparser-0.2.0.dist-info/METADATA
stparser-0.2.0.dist-info/RECORD
