Metadata-Version: 2.1
Name: stparser
Version: 0.2.0
Summary: A tool to convert strings to types. Primary use case is type specifications in configuration files.
Author: Patrick Wells
Author-email: pwells@ucdavis.edu
Requires-Python: >=3.8,<4.0
Classifier: Programming Language :: Python :: 3
Classifier: Programming Language :: Python :: 3.10
Classifier: Programming Language :: Python :: 3.8
Classifier: Programming Language :: Python :: 3.9
